projeta21/__init__.py
projeta21-1.5.dist-info/METADATA
projeta21-1.5.dist-info/WHEEL
projeta21-1.5.dist-info/top_level.txt
projeta21-1.5.dist-info/RECORD
