Metadata-Version: 2.1
Name: projeta21
Version: 1.5
Summary: Projet GCB202 A21
Home-page: https://catalyseur.ca
Author: Francis B. Lavoie
Author-email: francis.b.lavoie@usherbrooke.ca
License: UNKNOWN
Platform: UNKNOWN
Classifier: Programming Language :: Python :: 3
Classifier: License :: OSI Approved :: MIT License
Classifier: Operating System :: OS Independent
